arpa2.shell-0.1.0-py3.7-nspkg.pth
arpa2/shell/amqp/__init__.py
arpa2/shell/amqp/client.py
arpa2/shell/amqp/server.py
arpa2/shell/cmdparser/__init__.py
arpa2/shell/cmdparser/cmdparser.py
arpa2/shell/cmdparser/datetimeparse.py
arpa2/shell/cmdshell/__init__.py
arpa2/shell/cmdshell/base.py
arpa2/shell/cmdshell/meta.py
arpa2.shell-0.1.0.dist-info/METADATA
arpa2.shell-0.1.0.dist-info/WHEEL
arpa2.shell-0.1.0.dist-info/entry_points.txt
arpa2.shell-0.1.0.dist-info/namespace_packages.txt
arpa2.shell-0.1.0.dist-info/top_level.txt
arpa2.shell-0.1.0.dist-info/RECORD
