Metadata-Version: 2.1
Name: arpa2.shell
Version: 0.1.0
Summary: Generic ARPA2 commandline shell support -- shell switching -- JSON/AMQP backend
Home-page: https://gitlab.com/arpa2/shell
Author: Rick van Rein (for the ARPA2 Shell project)
Author-email: rick@openfortress.nl
License: UNKNOWN
Platform: UNKNOWN
Requires-Dist: six
Requires-Dist: enum34 ; python_version < "3"
Provides-Extra: json
Requires-Dist: gssapi ; extra == 'json'
Requires-Dist: python-qpid-proton ; extra == 'json'
